pyhepmc/__init__.py
pyhepmc/_attributes.py
pyhepmc/_autodoc.py
pyhepmc/_core.cp311-win_arm64.pyd
pyhepmc/_deprecated.py
pyhepmc/_doc.py
pyhepmc/_graphviz.py
pyhepmc/_prettify.py
pyhepmc/_setup.py
pyhepmc/io.py
pyhepmc/view.py
pyhepmc-2.16.1.dist-info/licenses/LICENSE
pyhepmc-2.16.1.dist-info/licenses/LICENSES_bundled
pyhepmc-2.16.1.dist-info/METADATA
pyhepmc-2.16.1.dist-info/WHEEL
pyhepmc-2.16.1.dist-info/top_level.txt
pyhepmc-2.16.1.dist-info/RECORD
