Metadata-Version: 2.4
Name: pyhepmc
Version: 2.16.1
Summary: Pythonic interface to the HepMC3 C++ library licensed under LGPL-v3.
Maintainer-email: Hans Dembinski <hans.dembinski@gmail.com>
Project-URL: repository, https://github.com/scikit-hep/pyhepmc
Project-URL: documentation, https://scikit-hep.org/pyhepmc
Classifier: Development Status :: 5 - Production/Stable
Classifier: License :: OSI Approved :: BSD License
Classifier: Programming Language :: Python :: 3
Classifier: Operating System :: POSIX :: Linux
Classifier: Operating System :: MacOS
Classifier: Operating System :: Microsoft :: Windows
Classifier: Topic :: Scientific/Engineering
Classifier: Intended Audience :: Developers
Requires-Python: >=3.9
License-File: LICENSE
License-File: LICENSES_bundled
Requires-Dist: numpy>=1.21
Requires-Dist: packaging
Requires-Dist: backports.zstd; python_version < "3.14"
Provides-Extra: test
Requires-Dist: pytest; extra == "test"
Requires-Dist: particle; extra == "test"
Requires-Dist: matplotlib; ((platform_system != "Windows" or python_version < "3.12") and (platform_system != "Linux" or platform_machine != "aarch64")) and extra == "test"
Provides-Extra: doc
Requires-Dist: sphinx; extra == "doc"
Requires-Dist: sphinx-rtd-theme; extra == "doc"
Requires-Dist: nbsphinx; extra == "doc"
Requires-Dist: ipython; extra == "doc"
Requires-Dist: ipykernel; extra == "doc"
Dynamic: license-file
